{
    "resetFormOnClick": true,
    "boxShadow": "none",
    "mobileBottomRow": 37,
    "widgetName": "Button2",
    "buttonColor": "{{appsmith.theme.colors.primaryColor}}",
    "displayName": "Button",
    "iconSVG": "/static/media/icon.7beb9123fb53027d9d6b778cdfe4caed.svg",
    "searchTags": [
        "click",
        "submit"
    ],
    "topRow": 60,
    "bottomRow": 64,
    "type": "BUTTON_WIDGET",
    "hideCard": false,
    "mobileRightColumn": 46,
    "animateLoading": true,
    "leftColumn": 25,
    "dynamicBindingPathList": [
        {"key": "buttonColor"},
        {"key": "borderRadius"}
    ],
    "text": "Reset",
    "isDisabled": false,
    "key": "5dfp6tqkw6",
    "isDeprecated": false,
    "rightColumn": 41,
    "isDefaultClickDisabled": true,
    "widgetId": "sd1661m3fo",
    "minWidth": 120,
    "isVisible": true,
    "recaptchaType": "V3",
    "version": 1,
    "parentId": "rpln55e14m",
    "renderMode": "CANVAS",
    "isLoading": false,
    "mobileTopRow": 33,
    "responsiveBehavior": "hug",
    "originalTopRow": 58,
    "disabledWhenInvalid": false,
    "borderRadius": "{{appsmith.theme.borderRadius.appBorderRadius}}",
    "mobileLeftColumn": 30,
    "originalBottomRow": 62,
    "buttonVariant": "SECONDARY",
    "placement": "CENTER"
}